README
setup.py
pylint2tusar/__init__.py
pylint2tusar/reporter.py
pylint2tusar.egg-info/PKG-INFO
pylint2tusar.egg-info/SOURCES.txt
pylint2tusar.egg-info/dependency_links.txt
pylint2tusar.egg-info/not-zip-safe
pylint2tusar.egg-info/requires.txt
pylint2tusar.egg-info/top_level.txt