Metadata-Version: 1.0
Name: pylint2tusar
Version: 0.3
Summary: PyLint plugin to allow TUSAR output format
Home-page: http://pypi.python.org/pypi/pylint2tusar
Author: Robin Jarry
Author-email: robin.jarry@gmail.com
License: MIT
Download-URL: http://pypi.python.org/pypi/pylint2tusar
Platform: any
Classifier: Development Status :: 4 - Beta
Classifier: Environment :: Console
Classifier: Environment :: Plugins
Classifier: Intended Audience :: Developers
Classifier: License :: OSI Approved :: MIT License
Classifier: Operating System :: OS Independent
Classifier: Programming Language :: Python
Classifier: Programming Language :: Python :: 2
Classifier: Topic :: Documentation
Classifier: Topic :: Text Processing
Classifier: Topic :: Utilities
